jsonllm/__init__.py
jsonllm/completions.py
jsonllm/constants.py
jsonllm/jsonllm.py
jsonllm/schema.py
jsonllm/utils.py
python_jsonllm-0.0.3.1.dist-info/LICENSE
python_jsonllm-0.0.3.1.dist-info/METADATA
python_jsonllm-0.0.3.1.dist-info/WHEEL
python_jsonllm-0.0.3.1.dist-info/top_level.txt
python_jsonllm-0.0.3.1.dist-info/RECORD
