Metadata-Version: 2.1
Name: python-jsonllm
Version: 0.0.3.1
Summary: LLM please cast to JSON
Home-page: https://github.com/ivanbelenky/jsonllm
Author: Ivan Belenky
License: MIT
Classifier: Programming Language :: Python :: 3
Classifier: License :: OSI Approved :: MIT License
Requires-Python: >=3.8
License-File: LICENSE
Requires-Dist: retry ==0.9.2
Requires-Dist: vertexai ==1.43.0
Requires-Dist: openai ==1.14.2
Requires-Dist: google-cloud-aiplatform ==1.44.0
Requires-Dist: tiktoken ==0.6.0
Requires-Dist: anthropic ==0.21.3
Requires-Dist: python-dotenv ==1.0.1
